[{"id":"b2e3072c.3bd368","type":"tab","label":"Flow 1","disabled":false,"info":""},{"id":"5c4eb853.876538","type":"inject","z":"b2e3072c.3bd368","name":"","topic":"","payload":"checkWeb","payloadType":"str","repeat":"30","crontab":"","once":true,"onceDelay":"10","x":370,"y":380,"wires":[["fed65a8c.b85cd8"]]},{"id":"fed65a8c.b85cd8","type":"ui_template","z":"b2e3072c.3bd368","group":"cb850534.b89e18","name":"Just a view of cameras","order":1,"width":"35","height":"16","format":"<!DOCTYPE html>\n<html>\n<style>\nimg {\n    border: 1px solid #ddd;\n    border-radius: 8px;\n    padding: 2px;\n    width: 405px;\n}\n</style>\n\n<script type=\"text/javascript\">\nscope.$watch('msg', function(msg) {\n    inMessage(msg.payload);\n});\n\nfunction updatePic() {\n    document.getElementById('c51').src = \"http://10.10.10.56:8001/?action=stream\";\n    document.getElementById('c52').src = \"http://10.10.10.56:8002/?action=stream\";\n    document.getElementById('c53').src = \"http://10.10.10.56:8003/?action=stream\";\n    document.getElementById('c54').src = \"http://10.10.10.56:8004/?action=stream\";\n    document.getElementById('c55').src = \"http://10.10.10.56:8006/?action=stream\";\n    //document.getElementById('c56').src = \"http://10.10.10.56:8006/?action=stream\";\n    //alert('updated pics');\n}\n\nfunction inMessage(event) {\n    if (event.match('checkWeb')) {\n        updatePic();\n    }\n}\n\n</script>\n<center>\n<table>\n    <tr><!-- Row 1 -->\n    \t\t<td style=\"text-align: center\"><img src=\"\" id=\"c51\" /></td>\n    \t\t<td style=\"text-align: center\"><img src=\"\" id=\"c52\" /></td>\n    \t\t<td style=\"text-align: center\"><img src=\"\" id=\"c53\" /></td>\n    </tr>\n    <tr><!-- Row 2 -->\n    \t    <td style=\"text-align: center\"><img src=\"\" id=\"c54\" /></td>\n    \t\t<td style=\"text-align: center\"><img src=\"\" id=\"c55\" /></td>\n    \t    \n    </tr>\n</table>\n</center>\n</html>","storeOutMessages":false,"fwdInMessages":false,"resendOnRefresh":false,"templateScope":"local","x":600,"y":380,"wires":[[]]},{"id":"7aa8d7f9.564a28","type":"ui_template","z":"b2e3072c.3bd368","group":"cb850534.b89e18","name":"Clock Toolbar","order":5,"width":"0","height":"0","format":"\n<script id=\"titleScript\" type=\"text/javascript\">\n    $('#clock').remove();\n    var toolbar = $('.md-toolbar-tools');\n    var div = $('<div></div>');\n    var p = $('<p/ id=\"clock\">');\n    $('#titleScript').parent().hide();\n    div.append(p);\n    div[0].style.margin = '5px 5px 5px auto';\n    toolbar.append(div);\n\n    function displayTitle(lh) {\n        p.text(lh); \n    }\n    \n    function upTime() {\n        var d = new Date();\n        p.text(d.toLocaleTimeString('de-AT'));\n    }\n\n    // Watch the payload and update the title\n    (function(scope) {\n        scope.$watch('msg.payload', function(data) {\n            if (data.match(\"systemsummary\")) { //Systemstatus\n                m = data;\n                n = m.split(':');\n                //alert(n[1]);\n                var sSummary = parseInt(n[1], 10);\n                if(sSummary === 14){\n                    document.getElementById(\"clock\").style.backgroundColor =\"transparent\";\n                }\n                if(sSummary < 14){\n                    document.getElementById(\"clock\").style.backgroundColor =\"#FF0033\";\n                }\n            }else{\n                displayTitle(data);\n            }\n        });\n        setInterval(upTime,1000);\n    })(scope);\n</script>","storeOutMessages":false,"fwdInMessages":false,"resendOnRefresh":false,"templateScope":"local","x":380,"y":320,"wires":[[]]},{"id":"cb850534.b89e18","type":"ui_group","z":"","name":"LiveVideo","tab":"bcc51c81.eb46c8","order":1,"disp":false,"width":"35","collapse":false},{"id":"bcc51c81.eb46c8","type":"ui_tab","z":"","name":"LiveVideo","icon":"dashboard","disabled":false,"hidden":false}]